pyVulkan
